dynimg/__init__.py
dynimg/__init__.pyi
dynimg/_dynimg.abi3.so
dynimg/py.typed
dynimg-0.1.13.dist-info/METADATA
dynimg-0.1.13.dist-info/WHEEL
dynimg-0.1.13.dist-info/licenses/LICENSE
dynimg.libs/libbz2-a273e504.so.1
dynimg.libs/libfontconfig-42c558d2.so.1
dynimg.libs/libfreetype-c0e61f0c.so.6
dynimg.libs/libpng15-ce838cd1.so.15
dynimg.libs/libuuid-f64cda11.so.1
dynimg-0.1.13.dist-info/RECORD
