Metadata-Version: 2.4
Name: dynimg
Version: 0.1.13
Classifier: Development Status :: 4 - Beta
Classifier: Intended Audience :: Developers
Classifier: License :: OSI Approved :: MIT License
Classifier: Operating System :: MacOS
Classifier: Operating System :: POSIX :: Linux
Classifier: Programming Language :: Python :: 3
Classifier: Programming Language :: Python :: 3.11
Classifier: Programming Language :: Python :: 3.12
Classifier: Programming Language :: Python :: 3.13
Classifier: Programming Language :: Rust
Classifier: Topic :: Multimedia :: Graphics
Classifier: Topic :: Internet :: WWW/HTTP :: Dynamic Content
License-File: LICENSE
Summary: A fast library for rendering HTML/CSS to images
Keywords: html,css,image,render,screenshot,og-image
License: MIT
Requires-Python: >=3.11
Project-URL: Homepage, https://github.com/blopker/dynimg
Project-URL: Repository, https://github.com/blopker/dynimg
